README.rst
setup.py
jsplit/__init__.py
jsplit/__main__.py
jsplit.egg-info/PKG-INFO
jsplit.egg-info/SOURCES.txt
jsplit.egg-info/dependency_links.txt
jsplit.egg-info/top_level.txt