Metadata-Version: 1.1
Name: jsplit
Version: 0.1.0
Summary: Split a JSON file into pieces.
Home-page: https://github.com/korzeniewskipl/jsplit
Author: Pawel Korzeniewski
Author-email: pawel@korzeniewski.pl
License: UNKNOWN
Platform: UNKNOWN
Classifier: Development Status :: 3 - Alpha
Classifier: Programming Language :: Python :: 2
Classifier: Programming Language :: Python :: 2.7
Classifier: Programming Language :: Python :: 3
Classifier: Programming Language :: Python :: 3.4
